<labeldata>
<lbx:ot>﻿ The </lbx:ot><aocr:verbatimInstitution>New York Botanical Garden</aocr:verbatimInstitution><dwc:datasetName>LICHENS OF FLORIDA</dwc:datasetName><dwc:country>U.S.A.</dwc:country><lbx:ot>Arthopyrenia cinchonae (Ach.) Müll. Arg. </lbx:ot><dwc:county>Dixie</dwc:county><lbx:ot>County: Steinhatchee Wildlife Management Area, along Andrew Sauls Rd., ca. 0.4 mi N of Co. Rd. 351 just N of Scrub Creek Baptist Church, ca. 6 mi NE of Cross City, 29°41'N, 83°04'W; oak scrub and oak woods near pond. </lbx:ot><dwc:verbatimEventDate>4 December 1993</dwc:verbatimEventDate><dwc:recordedBy>Richard C. Harris</dwc:recordedBy><dwc:recordNumber>31614</dwc:recordNumber><aocr:verbatimInstitution>New York Botanical Garden</aocr:verbatimInstitution><lbx:ot>01075828 </lbx:ot>
</labeldata>
