<?xml version="1.0" encoding="UTF-8"?>
<?xml-model href="http://herbis.arl.arizona.edu/DarwinsBiSciCol.rng" type="application/xml" schematypens="http://relaxng.org/ns/structure/1.0"?>
<labeldata>
<lbx:ot>0 </lbx:ot><lbx:ot>1 </lbx:ot><lbx:ot>2 </lbx:ot><lbx:ot>3 </lbx:ot><lbx:ot>4 </lbx:ot><lbx:ot>5 </lbx:ot><lbx:ot>6 </lbx:ot><lbx:ot>7 </lbx:ot><lbx:ot>8 </lbx:ot><lbx:ot>9 </lbx:ot><lbx:ot>10 </lbx:ot><lbx:ot>cm </lbx:ot><lbx:ot>copyright </lbx:ot><lbx:ot>reserved </lbx:ot><lbx:ot>The </lbx:ot><lbx:ot>New </lbx:ot><lbx:ot>York </lbx:ot><lbx:ot>Botanical </lbx:ot><lbx:ot>Garden </lbx:ot><lbx:ot>NEW </lbx:ot><lbx:ot>YORK </lbx:ot><lbx:ot>BOTANICAL </lbx:ot><lbx:ot>GARDEN </lbx:ot><lbx:ot>00198980 </lbx:ot><lbx:ot>NEW </lbx:ot><lbx:ot>YORK </lbx:ot><lbx:ot>BOTANICAL </lbx:ot><lbx:ot>GARDEN </lbx:ot><lbx:ot>Nothopanax </lbx:ot><lbx:ot>fruticosum </lbx:ot><lbx:ot>(L.) </lbx:ot><lbx:ot>Miq. </lbx:ot><lbx:ot>Determined </lbx:ot><lbx:ot>by </lbx:ot><lbx:ot>A. </lbx:ot><lbx:ot>C. </lbx:ot><lbx:ot>Smith, </lbx:ot><lbx:ot>1936. </lbx:ot><lbx:ot>NEW </lbx:ot><lbx:ot>YORK </lbx:ot><lbx:ot>BOTANICAL </lbx:ot><lbx:ot>GARDEN </lbx:ot><lbx:ot>CARNEGIE </lbx:ot><lbx:ot>INSTITUTION </lbx:ot><lbx:ot>OF </lbx:ot><lbx:ot>WASHINGTON </lbx:ot><lbx:ot>UNITED </lbx:ot><lbx:ot>STATES </lbx:ot><lbx:ot>NATIONAL </lbx:ot><lbx:ot>MUSEUM </lbx:ot><dwc:datasetName>WEST INDIAN EXPLORATION 1913</dwc:datasetName><dwc:stateProvince>ST. Thomas</dwc:stateProvince><lbx:ot>NO.- </lbx:ot><lbx:ot>Polyscias </lbx:ot><lbx:ot>filicifolia </lbx:ot><lbx:ot>(Moore) </lbx:ot><lbx:ot>Bailey </lbx:ot><lbx:ot>Cultivated, </lbx:ot><lbx:ot>Charlotte </lbx:ot><lbx:ot>Amelie </lbx:ot><lbx:ot>E. </lbx:ot><lbx:ot>G. </lbx:ot><lbx:ot>BRITTON </lbx:ot><lbx:ot>}COLLECTORS </lbx:ot><lbx:ot>DELIA </lbx:ot><lbx:ot>W. </lbx:ot><lbx:ot>MARBLE </lbx:ot><lbx:ot>FEBRUARY </lbx:ot><lbx:ot>27, </lbx:ot><dwc:verbatimEventDate>1913</dwc:verbatimEventDate>
</labeldata>
